[{"HOSTNAME": "public-vpn-156.opengw.net", "LOCATION": "Japan", "FLAG": "https://raw.githubusercontent.com/FreeSSTP/server-list/main/flags/JP.png", "PING": "14 ms", "PORT": 443, "UPTIME": "35 days", "SESSIONS": 223, "LINE_QUALITY": "1,802.05 Mbps", "SCORE": 3106336}, {"HOSTNAME": "vpn900625277.opengw.net", "LOCATION": "United States", "FLAG": "https://raw.githubusercontent.com/FreeSSTP/server-list/main/flags/US.png", "PING": "60 ms", "PORT": 1601, "UPTIME": "8 days", "SESSIONS": 65, "LINE_QUALITY": "7.96 Mbps", "SCORE": 3104090}, {"HOSTNAME": "public-vpn-105.opengw.net", "LOCATION": "Japan", "FLAG": "https://raw.githubusercontent.com/FreeSSTP/server-list/main/flags/JP.png", "PING": "16 ms", "PORT": 443, "UPTIME": "35 days", "SESSIONS": 260, "LINE_QUALITY": "1,524.77 Mbps", "SCORE": 3001253}, {"HOSTNAME": "public-vpn-205.opengw.net", "LOCATION": "Japan", "FLAG": "https://raw.githubusercontent.com/FreeSSTP/server-list/main/flags/JP.png", "PING": "14 ms", "PORT": 443, "UPTIME": "35 days", "SESSIONS": 198, "LINE_QUALITY": "1,223.88 Mbps", "SCORE": 2843453}, {"HOSTNAME": "public-vpn-44.opengw.net", "LOCATION": "Japan", "FLAG": "https://raw.githubusercontent.com/FreeSSTP/server-list/main/flags/JP.png", "PING": "25 ms", "PORT": 443, "UPTIME": "35 days", "SESSIONS": 237, "LINE_QUALITY": "2,114.02 Mbps", "SCORE": 2703356}, {"HOSTNAME": "public-vpn-240.opengw.net", "LOCATION": "Japan", "FLAG": "https://raw.githubusercontent.com/FreeSSTP/server-list/main/flags/JP.png", "PING": "16 ms", "PORT": 443, "UPTIME": "35 days", "SESSIONS": 230, "LINE_QUALITY": "1,171.02 Mbps", "SCORE": 2310741}, {"HOSTNAME": "public-vpn-253.opengw.net", "LOCATION": "Japan", "FLAG": "https://raw.githubusercontent.com/FreeSSTP/server-list/main/flags/JP.png", "PING": "19 ms", "PORT": 443, "UPTIME": "35 days", "SESSIONS": 273, "LINE_QUALITY": "4,758.18 Mbps", "SCORE": 2014134}, {"HOSTNAME": "public-vpn-46.opengw.net", "LOCATION": "Japan", "FLAG": "https://raw.githubusercontent.com/FreeSSTP/server-list/main/flags/JP.png", "PING": "17 ms", "PORT": 443, "UPTIME": "35 days", "SESSIONS": 193, "LINE_QUALITY": "1,963.99 Mbps", "SCORE": 1969485}, {"HOSTNAME": "public-vpn-119.opengw.net", "LOCATION": "Japan", "FLAG": "https://raw.githubusercontent.com/FreeSSTP/server-list/main/flags/JP.png", "PING": "25 ms", "PORT": 443, "UPTIME": "35 days", "SESSIONS": 315, "LINE_QUALITY": "3,094.46 Mbps", "SCORE": 1936454}, {"HOSTNAME": "vpn297981292.opengw.net", "LOCATION": "United States", "FLAG": "https://raw.githubusercontent.com/FreeSSTP/server-list/main/flags/US.png", "PING": "15 ms", "PORT": 1748, "UPTIME": "0 mins", "SESSIONS": 12, "LINE_QUALITY": "423.50 Mbps", "SCORE": 1919170}, {"HOSTNAME": "public-vpn-43.opengw.net", "LOCATION": "Japan", "FLAG": "https://raw.githubusercontent.com/FreeSSTP/server-list/main/flags/JP.png", "PING": "12 ms", "PORT": 443, "UPTIME": "35 days", "SESSIONS": 266, "LINE_QUALITY": "1,774.30 Mbps", "SCORE": 1918163}, {"HOSTNAME": "vpn169569844.opengw.net", "LOCATION": "United States", "FLAG": "https://raw.githubusercontent.com/FreeSSTP/server-list/main/flags/US.png", "PING": "10 ms", "PORT": 1595, "UPTIME": "0 mins", "SESSIONS": 38, "LINE_QUALITY": "133.56 Mbps", "SCORE": 1918134}, {"HOSTNAME": "public-vpn-225.opengw.net", "LOCATION": "Japan", "FLAG": "https://raw.githubusercontent.com/FreeSSTP/server-list/main/flags/JP.png", "PING": "21 ms", "PORT": 443, "UPTIME": "35 days", "SESSIONS": 256, "LINE_QUALITY": "3,143.90 Mbps", "SCORE": 1865605}, {"HOSTNAME": "public-vpn-244.opengw.net", "LOCATION": "Japan", "FLAG": "https://raw.githubusercontent.com/FreeSSTP/server-list/main/flags/JP.png", "PING": "29 ms", "PORT": 443, "UPTIME": "35 days", "SESSIONS": 273, "LINE_QUALITY": "4,729.20 Mbps", "SCORE": 1630245}, {"HOSTNAME": "vpn863361285.opengw.net", "LOCATION": "Viet Nam", "FLAG": "https://raw.githubusercontent.com/FreeSSTP/server-list/main/flags/VN.png", "PING": "26 ms", "PORT": 1257, "UPTIME": "10 days", "SESSIONS": 85, "LINE_QUALITY": "55.57 Mbps", "SCORE": 1535207}, {"HOSTNAME": "vpn984674298.opengw.net", "LOCATION": "Japan", "FLAG": "https://raw.githubusercontent.com/FreeSSTP/server-list/main/flags/JP.png", "PING": "2 ms", "PORT": 995, "UPTIME": "14 days", "SESSIONS": 110, "LINE_QUALITY": "647.08 Mbps", "SCORE": 1493545}, {"HOSTNAME": "vpn122289752.opengw.net", "LOCATION": "Korea Republic of", "FLAG": "https://raw.githubusercontent.com/FreeSSTP/server-list/main/flags/KR.png", "PING": "28 ms", "PORT": 995, "UPTIME": "13 days", "SESSIONS": 70, "LINE_QUALITY": "79.05 Mbps", "SCORE": 1453673}, {"HOSTNAME": "vpn135418552.opengw.net", "LOCATION": "Korea Republic of", "FLAG": "https://raw.githubusercontent.com/FreeSSTP/server-list/main/flags/KR.png", "PING": "31 ms", "PORT": 1751, "UPTIME": "9 days", "SESSIONS": 0, "LINE_QUALITY": "454.81 Mbps", "SCORE": 1450476}, {"HOSTNAME": "public-vpn-122.opengw.net", "LOCATION": "Japan", "FLAG": "https://raw.githubusercontent.com/FreeSSTP/server-list/main/flags/JP.png", "PING": "20 ms", "PORT": 443, "UPTIME": "35 days", "SESSIONS": 262, "LINE_QUALITY": "1,558.57 Mbps", "SCORE": 1442537}, {"HOSTNAME": "vpn609936379.opengw.net", "LOCATION": "Viet Nam", "FLAG": "https://raw.githubusercontent.com/FreeSSTP/server-list/main/flags/VN.png", "PING": "28 ms", "PORT": 1726, "UPTIME": "7 days", "SESSIONS": 82, "LINE_QUALITY": "434.77 Mbps", "SCORE": 1424765}, {"HOSTNAME": "vpn132685462.opengw.net", "LOCATION": "Korea Republic of", "FLAG": "https://raw.githubusercontent.com/FreeSSTP/server-list/main/flags/KR.png", "PING": "49 ms", "PORT": 1830, "UPTIME": "15 days", "SESSIONS": 67, "LINE_QUALITY": "75.39 Mbps", "SCORE": 1413985}, {"HOSTNAME": "vpn653613602.opengw.net", "LOCATION": "Korea Republic of", "FLAG": "https://raw.githubusercontent.com/FreeSSTP/server-list/main/flags/KR.png", "PING": "27 ms", "PORT": 1870, "UPTIME": "62 days", "SESSIONS": 90, "LINE_QUALITY": "65.89 Mbps", "SCORE": 1410177}, {"HOSTNAME": "vpn201242416.opengw.net", "LOCATION": "Korea Republic of", "FLAG": "https://raw.githubusercontent.com/FreeSSTP/server-list/main/flags/KR.png", "PING": "31 ms", "PORT": 995, "UPTIME": "31 days", "SESSIONS": 86, "LINE_QUALITY": "71.59 Mbps", "SCORE": 1406919}, {"HOSTNAME": "public-vpn-184.opengw.net", "LOCATION": "Japan", "FLAG": "https://raw.githubusercontent.com/FreeSSTP/server-list/main/flags/JP.png", "PING": "17 ms", "PORT": 443, "UPTIME": "35 days", "SESSIONS": 365, "LINE_QUALITY": "3,717.30 Mbps", "SCORE": 1401802}, {"HOSTNAME": "vpn492467730.opengw.net", "LOCATION": "Viet Nam", "FLAG": "https://raw.githubusercontent.com/FreeSSTP/server-list/main/flags/VN.png", "PING": "35 ms", "PORT": 1255, "UPTIME": "9 days", "SESSIONS": 84, "LINE_QUALITY": "192.23 Mbps", "SCORE": 1397496}, {"HOSTNAME": "vpn699936467.opengw.net", "LOCATION": "Korea Republic of", "FLAG": "https://raw.githubusercontent.com/FreeSSTP/server-list/main/flags/KR.png", "PING": "37 ms", "PORT": 1317, "UPTIME": "34 days", "SESSIONS": 91, "LINE_QUALITY": "354.74 Mbps", "SCORE": 1395845}, {"HOSTNAME": "public-vpn-45.opengw.net", "LOCATION": "Japan", "FLAG": "https://raw.githubusercontent.com/FreeSSTP/server-list/main/flags/JP.png", "PING": "16 ms", "PORT": 443, "UPTIME": "35 days", "SESSIONS": 229, "LINE_QUALITY": "1,899.63 Mbps", "SCORE": 1395713}, {"HOSTNAME": "public-vpn-224.opengw.net", "LOCATION": "Japan", "FLAG": "https://raw.githubusercontent.com/FreeSSTP/server-list/main/flags/JP.png", "PING": "10 ms", "PORT": 443, "UPTIME": "35 days", "SESSIONS": 270, "LINE_QUALITY": "4,336.11 Mbps", "SCORE": 1386762}, {"HOSTNAME": "vpn305806016.opengw.net", "LOCATION": "Korea Republic of", "FLAG": "https://raw.githubusercontent.com/FreeSSTP/server-list/main/flags/KR.png", "PING": "30 ms", "PORT": 995, "UPTIME": "6 days", "SESSIONS": 78, "LINE_QUALITY": "368.82 Mbps", "SCORE": 1336933}, {"HOSTNAME": "public-vpn-53.opengw.net", "LOCATION": "Japan", "FLAG": "https://raw.githubusercontent.com/FreeSSTP/server-list/main/flags/JP.png", "PING": "28 ms", "PORT": 443, "UPTIME": "35 days", "SESSIONS": 19, "LINE_QUALITY": "1,683.85 Mbps", "SCORE": 1327359}, {"HOSTNAME": "vpn235869316.opengw.net", "LOCATION": "Japan", "FLAG": "https://raw.githubusercontent.com/FreeSSTP/server-list/main/flags/JP.png", "PING": "2 ms", "PORT": 1382, "UPTIME": "5 days", "SESSIONS": 75, "LINE_QUALITY": "261.40 Mbps", "SCORE": 1323359}, {"HOSTNAME": "public-vpn-163.opengw.net", "LOCATION": "Japan", "FLAG": "https://raw.githubusercontent.com/FreeSSTP/server-list/main/flags/JP.png", "PING": "19 ms", "PORT": 443, "UPTIME": "35 days", "SESSIONS": 299, "LINE_QUALITY": "2,867.37 Mbps", "SCORE": 1306834}, {"HOSTNAME": "vpn718368553.opengw.net", "LOCATION": "Korea Republic of", "FLAG": "https://raw.githubusercontent.com/FreeSSTP/server-list/main/flags/KR.png", "PING": "-", "PORT": 1226, "UPTIME": "11 days", "SESSIONS": 68, "LINE_QUALITY": "147.70 Mbps", "SCORE": 1299146}, {"HOSTNAME": "public-vpn-82.opengw.net", "LOCATION": "Japan", "FLAG": "https://raw.githubusercontent.com/FreeSSTP/server-list/main/flags/JP.png", "PING": "15 ms", "PORT": 443, "UPTIME": "35 days", "SESSIONS": 250, "LINE_QUALITY": "2,535.35 Mbps", "SCORE": 1285643}, {"HOSTNAME": "public-vpn-114.opengw.net", "LOCATION": "Japan", "FLAG": "https://raw.githubusercontent.com/FreeSSTP/server-list/main/flags/JP.png", "PING": "22 ms", "PORT": 443, "UPTIME": "35 days", "SESSIONS": 233, "LINE_QUALITY": "2,776.33 Mbps", "SCORE": 1266556}, {"HOSTNAME": "vpn545882156.opengw.net", "LOCATION": "Korea Republic of", "FLAG": "https://raw.githubusercontent.com/FreeSSTP/server-list/main/flags/KR.png", "PING": "37 ms", "PORT": 1379, "UPTIME": "5 days", "SESSIONS": 72, "LINE_QUALITY": "63.93 Mbps", "SCORE": 1219402}, {"HOSTNAME": "vpn445518024.opengw.net", "LOCATION": "Japan", "FLAG": "https://raw.githubusercontent.com/FreeSSTP/server-list/main/flags/JP.png", "PING": "13 ms", "PORT": 1511, "UPTIME": "4 days", "SESSIONS": 71, "LINE_QUALITY": "188.79 Mbps", "SCORE": 1218125}, {"HOSTNAME": "public-vpn-183.opengw.net", "LOCATION": "Japan", "FLAG": "https://raw.githubusercontent.com/FreeSSTP/server-list/main/flags/JP.png", "PING": "23 ms", "PORT": 443, "UPTIME": "35 days", "SESSIONS": 234, "LINE_QUALITY": "4,109.70 Mbps", "SCORE": 1199204}, {"HOSTNAME": "rinze.opengw.net", "LOCATION": "Japan", "FLAG": "https://raw.githubusercontent.com/FreeSSTP/server-list/main/flags/JP.png", "PING": "4 ms", "PORT": 443, "UPTIME": "47 days", "SESSIONS": 125, "LINE_QUALITY": "2.01 Mbps", "SCORE": 1156662}, {"HOSTNAME": "vpn773812232.opengw.net", "LOCATION": "Japan", "FLAG": "https://raw.githubusercontent.com/FreeSSTP/server-list/main/flags/JP.png", "PING": "20 ms", "PORT": 1593, "UPTIME": "3 days", "SESSIONS": 0, "LINE_QUALITY": "240.06 Mbps", "SCORE": 1054676}, {"HOSTNAME": "vpn440613432.opengw.net", "LOCATION": "Japan", "FLAG": "https://raw.githubusercontent.com/FreeSSTP/server-list/main/flags/JP.png", "PING": "18 ms", "PORT": 1509, "UPTIME": "2 days", "SESSIONS": 65, "LINE_QUALITY": "34.90 Mbps", "SCORE": 952289}, {"HOSTNAME": "vpn961082190.opengw.net", "LOCATION": "Japan", "FLAG": "https://raw.githubusercontent.com/FreeSSTP/server-list/main/flags/JP.png", "PING": "3 ms", "PORT": 1737, "UPTIME": "2 days", "SESSIONS": 70, "LINE_QUALITY": "791.65 Mbps", "SCORE": 946480}, {"HOSTNAME": "vpn158642350.opengw.net", "LOCATION": "Korea Republic of", "FLAG": "https://raw.githubusercontent.com/FreeSSTP/server-list/main/flags/KR.png", "PING": "28 ms", "PORT": 995, "UPTIME": "2 days", "SESSIONS": 67, "LINE_QUALITY": "107.38 Mbps", "SCORE": 917807}, {"HOSTNAME": "vpn831500470.opengw.net", "LOCATION": "Viet Nam", "FLAG": "https://raw.githubusercontent.com/FreeSSTP/server-list/main/flags/VN.png", "PING": "28 ms", "PORT": 1872, "UPTIME": "2 days", "SESSIONS": 43, "LINE_QUALITY": "491.01 Mbps", "SCORE": 883918}, {"HOSTNAME": "vpn838556596.opengw.net", "LOCATION": "Korea Republic of", "FLAG": "https://raw.githubusercontent.com/FreeSSTP/server-list/main/flags/KR.png", "PING": "27 ms", "PORT": 995, "UPTIME": "2 days", "SESSIONS": 106, "LINE_QUALITY": "375.05 Mbps", "SCORE": 881826}, {"HOSTNAME": "vpn866384313.opengw.net", "LOCATION": "Viet Nam", "FLAG": "https://raw.githubusercontent.com/FreeSSTP/server-list/main/flags/VN.png", "PING": "28 ms", "PORT": 1504, "UPTIME": "2 days", "SESSIONS": 23, "LINE_QUALITY": "520.43 Mbps", "SCORE": 870564}, {"HOSTNAME": "vpn958446343.opengw.net", "LOCATION": "Korea Republic of", "FLAG": "https://raw.githubusercontent.com/FreeSSTP/server-list/main/flags/KR.png", "PING": "29 ms", "PORT": 995, "UPTIME": "2 days", "SESSIONS": 67, "LINE_QUALITY": "398.79 Mbps", "SCORE": 869279}, {"HOSTNAME": "vpn927996807.opengw.net", "LOCATION": "Korea Republic of", "FLAG": "https://raw.githubusercontent.com/FreeSSTP/server-list/main/flags/KR.png", "PING": "29 ms", "PORT": 1243, "UPTIME": "2 days", "SESSIONS": 51, "LINE_QUALITY": "72.29 Mbps", "SCORE": 850459}, {"HOSTNAME": "vpn247310721.opengw.net", "LOCATION": "Japan", "FLAG": "https://raw.githubusercontent.com/FreeSSTP/server-list/main/flags/JP.png", "PING": "16 ms", "PORT": 1747, "UPTIME": "1 days", "SESSIONS": 41, "LINE_QUALITY": "539.38 Mbps", "SCORE": 844431}, {"HOSTNAME": "vpn722210664.opengw.net", "LOCATION": "Japan", "FLAG": "https://raw.githubusercontent.com/FreeSSTP/server-list/main/flags/JP.png", "PING": "112 ms", "PORT": 1787, "UPTIME": "2 days", "SESSIONS": 57, "LINE_QUALITY": "109.26 Mbps", "SCORE": 807685}, {"HOSTNAME": "vpn140592768.opengw.net", "LOCATION": "Japan", "FLAG": "https://raw.githubusercontent.com/FreeSSTP/server-list/main/flags/JP.png", "PING": "4 ms", "PORT": 1685, "UPTIME": "1 days", "SESSIONS": 52, "LINE_QUALITY": "94.66 Mbps", "SCORE": 796846}, {"HOSTNAME": "vpn624166971.opengw.net", "LOCATION": "Japan", "FLAG": "https://raw.githubusercontent.com/FreeSSTP/server-list/main/flags/JP.png", "PING": "5 ms", "PORT": 1608, "UPTIME": "1 days", "SESSIONS": 16, "LINE_QUALITY": "73.44 Mbps", "SCORE": 779089}, {"HOSTNAME": "vpn982111148.opengw.net", "LOCATION": "Japan", "FLAG": "https://raw.githubusercontent.com/FreeSSTP/server-list/main/flags/JP.png", "PING": "3 ms", "PORT": 1664, "UPTIME": "16 hours", "SESSIONS": 39, "LINE_QUALITY": "922.34 Mbps", "SCORE": 746901}, {"HOSTNAME": "vpn931865937.opengw.net", "LOCATION": "Japan", "FLAG": "https://raw.githubusercontent.com/FreeSSTP/server-list/main/flags/JP.png", "PING": "19 ms", "PORT": 1482, "UPTIME": "16 hours", "SESSIONS": 25, "LINE_QUALITY": "205.09 Mbps", "SCORE": 746442}, {"HOSTNAME": "vpn570051084.opengw.net", "LOCATION": "Viet Nam", "FLAG": "https://raw.githubusercontent.com/FreeSSTP/server-list/main/flags/VN.png", "PING": "30 ms", "PORT": 1786, "UPTIME": "1 days", "SESSIONS": 25, "LINE_QUALITY": "38.07 Mbps", "SCORE": 739839}, {"HOSTNAME": "vpn999934323.opengw.net", "LOCATION": "Japan", "FLAG": "https://raw.githubusercontent.com/FreeSSTP/server-list/main/flags/JP.png", "PING": "4 ms", "PORT": 1788, "UPTIME": "16 hours", "SESSIONS": 59, "LINE_QUALITY": "558.96 Mbps", "SCORE": 724113}, {"HOSTNAME": "vpn661089673.opengw.net", "LOCATION": "Japan", "FLAG": "https://raw.githubusercontent.com/FreeSSTP/server-list/main/flags/JP.png", "PING": "7 ms", "PORT": 1441, "UPTIME": "10 hours", "SESSIONS": 19, "LINE_QUALITY": "92.80 Mbps", "SCORE": 714316}, {"HOSTNAME": "vpn345595222.opengw.net", "LOCATION": "Japan", "FLAG": "https://raw.githubusercontent.com/FreeSSTP/server-list/main/flags/JP.png", "PING": "7 ms", "PORT": 1382, "UPTIME": "10 hours", "SESSIONS": 13, "LINE_QUALITY": "77.53 Mbps", "SCORE": 699209}, {"HOSTNAME": "vpn130978353.opengw.net", "LOCATION": "Korea Republic of", "FLAG": "https://raw.githubusercontent.com/FreeSSTP/server-list/main/flags/KR.png", "PING": "30 ms", "PORT": 995, "UPTIME": "1 days", "SESSIONS": 17, "LINE_QUALITY": "687.56 Mbps", "SCORE": 695836}, {"HOSTNAME": "2i6.opengw.net", "LOCATION": "Japan", "FLAG": "https://raw.githubusercontent.com/FreeSSTP/server-list/main/flags/JP.png", "PING": "20 ms", "PORT": 1194, "UPTIME": "6 hours", "SESSIONS": 48, "LINE_QUALITY": "211.72 Mbps", "SCORE": 695149}, {"HOSTNAME": "vpn698300610.opengw.net", "LOCATION": "Korea Republic of", "FLAG": "https://raw.githubusercontent.com/FreeSSTP/server-list/main/flags/KR.png", "PING": "26 ms", "PORT": 1804, "UPTIME": "1 days", "SESSIONS": 17, "LINE_QUALITY": "62.84 Mbps", "SCORE": 693540}, {"HOSTNAME": "vpn343317219.opengw.net", "LOCATION": "Japan", "FLAG": "https://raw.githubusercontent.com/FreeSSTP/server-list/main/flags/JP.png", "PING": "21 ms", "PORT": 1491, "UPTIME": "6 hours", "SESSIONS": 24, "LINE_QUALITY": "264.39 Mbps", "SCORE": 682095}, {"HOSTNAME": "kozakura1234.opengw.net", "LOCATION": "Japan", "FLAG": "https://raw.githubusercontent.com/FreeSSTP/server-list/main/flags/JP.png", "PING": "31 ms", "PORT": 443, "UPTIME": "13 hours", "SESSIONS": 91, "LINE_QUALITY": "90.86 Mbps", "SCORE": 681175}, {"HOSTNAME": "vpn804569942.opengw.net", "LOCATION": "Viet Nam", "FLAG": "https://raw.githubusercontent.com/FreeSSTP/server-list/main/flags/VN.png", "PING": "29 ms", "PORT": 1845, "UPTIME": "16 hours", "SESSIONS": 45, "LINE_QUALITY": "426.58 Mbps", "SCORE": 676698}, {"HOSTNAME": "vpn142410485.opengw.net", "LOCATION": "Japan", "FLAG": "https://raw.githubusercontent.com/FreeSSTP/server-list/main/flags/JP.png", "PING": "4 ms", "PORT": 1693, "UPTIME": "10 hours", "SESSIONS": 10, "LINE_QUALITY": "95.74 Mbps", "SCORE": 667415}, {"HOSTNAME": "vpn556992420.opengw.net", "LOCATION": "Korea Republic of", "FLAG": "https://raw.githubusercontent.com/FreeSSTP/server-list/main/flags/KR.png", "PING": "25 ms", "PORT": 1907, "UPTIME": "13 hours", "SESSIONS": 18, "LINE_QUALITY": "95.36 Mbps", "SCORE": 660558}, {"HOSTNAME": "vpn332195449.opengw.net", "LOCATION": "Korea Republic of", "FLAG": "https://raw.githubusercontent.com/FreeSSTP/server-list/main/flags/KR.png", "PING": "32 ms", "PORT": 1539, "UPTIME": "16 hours", "SESSIONS": 35, "LINE_QUALITY": "86.44 Mbps", "SCORE": 657812}, {"HOSTNAME": "vpn656018120.opengw.net", "LOCATION": "Japan", "FLAG": "https://raw.githubusercontent.com/FreeSSTP/server-list/main/flags/JP.png", "PING": "8 ms", "PORT": 1742, "UPTIME": "10 hours", "SESSIONS": 25, "LINE_QUALITY": "87.56 Mbps", "SCORE": 656472}, {"HOSTNAME": "vpn215438181.opengw.net", "LOCATION": "Japan", "FLAG": "https://raw.githubusercontent.com/FreeSSTP/server-list/main/flags/JP.png", "PING": "2 ms", "PORT": 1443, "UPTIME": "6 hours", "SESSIONS": 26, "LINE_QUALITY": "743.53 Mbps", "SCORE": 655710}, {"HOSTNAME": "vpn936687919.opengw.net", "LOCATION": "Korea Republic of", "FLAG": "https://raw.githubusercontent.com/FreeSSTP/server-list/main/flags/KR.png", "PING": "30 ms", "PORT": 995, "UPTIME": "13 hours", "SESSIONS": 10, "LINE_QUALITY": "303.89 Mbps", "SCORE": 646577}, {"HOSTNAME": "vpn365572453.opengw.net", "LOCATION": "Japan", "FLAG": "https://raw.githubusercontent.com/FreeSSTP/server-list/main/flags/JP.png", "PING": "11 ms", "PORT": 1632, "UPTIME": "0 mins", "SESSIONS": 2, "LINE_QUALITY": "182.05 Mbps", "SCORE": 637867}, {"HOSTNAME": "vpn925379206.opengw.net", "LOCATION": "Korea Republic of", "FLAG": "https://raw.githubusercontent.com/FreeSSTP/server-list/main/flags/KR.png", "PING": "33 ms", "PORT": 995, "UPTIME": "13 hours", "SESSIONS": 15, "LINE_QUALITY": "85.83 Mbps", "SCORE": 637249}, {"HOSTNAME": "vpn221397876.opengw.net", "LOCATION": "Japan", "FLAG": "https://raw.githubusercontent.com/FreeSSTP/server-list/main/flags/JP.png", "PING": "9 ms", "PORT": 1993, "UPTIME": "0 mins", "SESSIONS": 10, "LINE_QUALITY": "176.43 Mbps", "SCORE": 624790}, {"HOSTNAME": "vpn555269421.opengw.net", "LOCATION": "Argentina", "FLAG": "https://raw.githubusercontent.com/FreeSSTP/server-list/main/flags/AR.png", "PING": "3 ms", "PORT": 1702, "UPTIME": "0 mins", "SESSIONS": 4, "LINE_QUALITY": "151.05 Mbps", "SCORE": 610389}, {"HOSTNAME": "vpn661203165.opengw.net", "LOCATION": "Korea Republic of", "FLAG": "https://raw.githubusercontent.com/FreeSSTP/server-list/main/flags/KR.png", "PING": "39 ms", "PORT": 995, "UPTIME": "10 hours", "SESSIONS": 11, "LINE_QUALITY": "294.53 Mbps", "SCORE": 599678}, {"HOSTNAME": "vpn827501246.opengw.net", "LOCATION": "Japan", "FLAG": "https://raw.githubusercontent.com/FreeSSTP/server-list/main/flags/JP.png", "PING": "28 ms", "PORT": 1530, "UPTIME": "6 hours", "SESSIONS": 9, "LINE_QUALITY": "78.37 Mbps", "SCORE": 587827}, {"HOSTNAME": "vpn625139581.opengw.net", "LOCATION": "Korea Republic of", "FLAG": "https://raw.githubusercontent.com/FreeSSTP/server-list/main/flags/KR.png", "PING": "36 ms", "PORT": 995, "UPTIME": "10 hours", "SESSIONS": 22, "LINE_QUALITY": "123.96 Mbps", "SCORE": 583128}, {"HOSTNAME": "vpn338874352.opengw.net", "LOCATION": "Korea Republic of", "FLAG": "https://raw.githubusercontent.com/FreeSSTP/server-list/main/flags/KR.png", "PING": "30 ms", "PORT": 995, "UPTIME": "6 hours", "SESSIONS": 7, "LINE_QUALITY": "680.28 Mbps", "SCORE": 573816}, {"HOSTNAME": "vpn731314702.opengw.net", "LOCATION": "Korea Republic of", "FLAG": "https://raw.githubusercontent.com/FreeSSTP/server-list/main/flags/KR.png", "PING": "36 ms", "PORT": 1820, "UPTIME": "6 hours", "SESSIONS": 2, "LINE_QUALITY": "85.68 Mbps", "SCORE": 573325}, {"HOSTNAME": "vpn909780280.opengw.net", "LOCATION": "Korea Republic of", "FLAG": "https://raw.githubusercontent.com/FreeSSTP/server-list/main/flags/KR.png", "PING": "41 ms", "PORT": 1748, "UPTIME": "16 hours", "SESSIONS": 11, "LINE_QUALITY": "73.80 Mbps", "SCORE": 571398}, {"HOSTNAME": "vpn407218410.opengw.net", "LOCATION": "Korea Republic of", "FLAG": "https://raw.githubusercontent.com/FreeSSTP/server-list/main/flags/KR.png", "PING": "37 ms", "PORT": 1848, "UPTIME": "6 hours", "SESSIONS": 17, "LINE_QUALITY": "695.82 Mbps", "SCORE": 570470}, {"HOSTNAME": "vpn858310545.opengw.net", "LOCATION": "Korea Republic of", "FLAG": "https://raw.githubusercontent.com/FreeSSTP/server-list/main/flags/KR.png", "PING": "32 ms", "PORT": 995, "UPTIME": "0 mins", "SESSIONS": 2, "LINE_QUALITY": "94.22 Mbps", "SCORE": 561807}, {"HOSTNAME": "vpn446446223.opengw.net", "LOCATION": "Korea Republic of", "FLAG": "https://raw.githubusercontent.com/FreeSSTP/server-list/main/flags/KR.png", "PING": "28 ms", "PORT": 1244, "UPTIME": "0 mins", "SESSIONS": 12, "LINE_QUALITY": "419.86 Mbps", "SCORE": 551712}, {"HOSTNAME": "vpn419684052.opengw.net", "LOCATION": "Korea Republic of", "FLAG": "https://raw.githubusercontent.com/FreeSSTP/server-list/main/flags/KR.png", "PING": "31 ms", "PORT": 995, "UPTIME": "0 mins", "SESSIONS": 11, "LINE_QUALITY": "95.94 Mbps", "SCORE": 548313}, {"HOSTNAME": "vpn823736106.opengw.net", "LOCATION": "Korea Republic of", "FLAG": "https://raw.githubusercontent.com/FreeSSTP/server-list/main/flags/KR.png", "PING": "29 ms", "PORT": 1413, "UPTIME": "0 mins", "SESSIONS": 8, "LINE_QUALITY": "88.36 Mbps", "SCORE": 546895}, {"HOSTNAME": "vpn683532116.opengw.net", "LOCATION": "Korea Republic of", "FLAG": "https://raw.githubusercontent.com/FreeSSTP/server-list/main/flags/KR.png", "PING": "36 ms", "PORT": 995, "UPTIME": "0 mins", "SESSIONS": 4, "LINE_QUALITY": "95.67 Mbps", "SCORE": 544132}]