[{"HOSTNAME": "public-vpn-198.opengw.net", "LOCATION": "Japan", "FLAG": "https://raw.githubusercontent.com/FreeSSTP/server-list/main/flags/JP.png", "PING": "21 ms", "PORT": 443, "UPTIME": "17 days", "SESSIONS": 217, "LINE_QUALITY": "55.55 Mbps", "SCORE": 2844615}, {"HOSTNAME": "public-vpn-242.opengw.net", "LOCATION": "Japan", "FLAG": "https://raw.githubusercontent.com/FreeSSTP/server-list/main/flags/JP.png", "PING": "12 ms", "PORT": 443, "UPTIME": "17 days", "SESSIONS": 122, "LINE_QUALITY": "48.46 Mbps", "SCORE": 2726740}, {"HOSTNAME": "public-vpn-129.opengw.net", "LOCATION": "Japan", "FLAG": "https://raw.githubusercontent.com/FreeSSTP/server-list/main/flags/JP.png", "PING": "30 ms", "PORT": 443, "UPTIME": "17 days", "SESSIONS": 104, "LINE_QUALITY": "93.72 Mbps", "SCORE": 2697540}, {"HOSTNAME": "public-vpn-131.opengw.net", "LOCATION": "Japan", "FLAG": "https://raw.githubusercontent.com/FreeSSTP/server-list/main/flags/JP.png", "PING": "11 ms", "PORT": 443, "UPTIME": "17 days", "SESSIONS": 204, "LINE_QUALITY": "14.87 Mbps", "SCORE": 2504396}, {"HOSTNAME": "public-vpn-133.opengw.net", "LOCATION": "Japan", "FLAG": "https://raw.githubusercontent.com/FreeSSTP/server-list/main/flags/JP.png", "PING": "14 ms", "PORT": 443, "UPTIME": "17 days", "SESSIONS": 178, "LINE_QUALITY": "79.91 Mbps", "SCORE": 2407004}, {"HOSTNAME": "public-vpn-216.opengw.net", "LOCATION": "Japan", "FLAG": "https://raw.githubusercontent.com/FreeSSTP/server-list/main/flags/JP.png", "PING": "16 ms", "PORT": 443, "UPTIME": "17 days", "SESSIONS": 163, "LINE_QUALITY": "98.99 Mbps", "SCORE": 2389262}, {"HOSTNAME": "public-vpn-98.opengw.net", "LOCATION": "Japan", "FLAG": "https://raw.githubusercontent.com/FreeSSTP/server-list/main/flags/JP.png", "PING": "8 ms", "PORT": 443, "UPTIME": "17 days", "SESSIONS": 339, "LINE_QUALITY": "10.27 Mbps", "SCORE": 2221416}, {"HOSTNAME": "public-vpn-97.opengw.net", "LOCATION": "Japan", "FLAG": "https://raw.githubusercontent.com/FreeSSTP/server-list/main/flags/JP.png", "PING": "20 ms", "PORT": 443, "UPTIME": "17 days", "SESSIONS": 173, "LINE_QUALITY": "66.82 Mbps", "SCORE": 2208418}, {"HOSTNAME": "public-vpn-161.opengw.net", "LOCATION": "Japan", "FLAG": "https://raw.githubusercontent.com/FreeSSTP/server-list/main/flags/JP.png", "PING": "11 ms", "PORT": 443, "UPTIME": "17 days", "SESSIONS": 531, "LINE_QUALITY": "14.35 Mbps", "SCORE": 2191110}, {"HOSTNAME": "public-vpn-241.opengw.net", "LOCATION": "Japan", "FLAG": "https://raw.githubusercontent.com/FreeSSTP/server-list/main/flags/JP.png", "PING": "13 ms", "PORT": 443, "UPTIME": "17 days", "SESSIONS": 235, "LINE_QUALITY": "195.38 Mbps", "SCORE": 1894289}, {"HOSTNAME": "public-vpn-253.opengw.net", "LOCATION": "Japan", "FLAG": "https://raw.githubusercontent.com/FreeSSTP/server-list/main/flags/JP.png", "PING": "8 ms", "PORT": 443, "UPTIME": "17 days", "SESSIONS": 311, "LINE_QUALITY": "44.37 Mbps", "SCORE": 1750748}, {"HOSTNAME": "vpn521576029.opengw.net", "LOCATION": "Australia", "FLAG": "https://raw.githubusercontent.com/FreeSSTP/server-list/main/flags/AU.png", "PING": "10 ms", "PORT": 1194, "UPTIME": "19 days", "SESSIONS": 60, "LINE_QUALITY": "83.14 Mbps", "SCORE": 1571606}, {"HOSTNAME": "vpn478340893.opengw.net", "LOCATION": "Japan", "FLAG": "https://raw.githubusercontent.com/FreeSSTP/server-list/main/flags/JP.png", "PING": "9 ms", "PORT": 1784, "UPTIME": "15 days", "SESSIONS": 63, "LINE_QUALITY": "80.34 Mbps", "SCORE": 1551531}, {"HOSTNAME": "vpn163318310.opengw.net", "LOCATION": "Japan", "FLAG": "https://raw.githubusercontent.com/FreeSSTP/server-list/main/flags/JP.png", "PING": "10 ms", "PORT": 1677, "UPTIME": "14 days", "SESSIONS": 41, "LINE_QUALITY": "74.38 Mbps", "SCORE": 1541866}, {"HOSTNAME": "public-vpn-64.opengw.net", "LOCATION": "Japan", "FLAG": "https://raw.githubusercontent.com/FreeSSTP/server-list/main/flags/JP.png", "PING": "12 ms", "PORT": 443, "UPTIME": "17 days", "SESSIONS": 185, "LINE_QUALITY": "7.55 Mbps", "SCORE": 1525629}, {"HOSTNAME": "vpn557874303.opengw.net", "LOCATION": "Korea Republic of", "FLAG": "https://raw.githubusercontent.com/FreeSSTP/server-list/main/flags/KR.png", "PING": "24 ms", "PORT": 995, "UPTIME": "24 days", "SESSIONS": 77, "LINE_QUALITY": "39.04 Mbps", "SCORE": 1523674}, {"HOSTNAME": "vpn0925204913.opengw.net", "LOCATION": "Taiwan", "FLAG": "https://raw.githubusercontent.com/FreeSSTP/server-list/main/flags/TW.png", "PING": "13 ms", "PORT": 992, "UPTIME": "15 days", "SESSIONS": 99, "LINE_QUALITY": "87.77 Mbps", "SCORE": 1507934}, {"HOSTNAME": "public-vpn-156.opengw.net", "LOCATION": "Japan", "FLAG": "https://raw.githubusercontent.com/FreeSSTP/server-list/main/flags/JP.png", "PING": "14 ms", "PORT": 443, "UPTIME": "17 days", "SESSIONS": 349, "LINE_QUALITY": "43.15 Mbps", "SCORE": 1467314}, {"HOSTNAME": "vpn573532402.opengw.net", "LOCATION": "Japan", "FLAG": "https://raw.githubusercontent.com/FreeSSTP/server-list/main/flags/JP.png", "PING": "2 ms", "PORT": 1974, "UPTIME": "50 days", "SESSIONS": 135, "LINE_QUALITY": "54.15 Mbps", "SCORE": 1448773}, {"HOSTNAME": "vpn749628453.opengw.net", "LOCATION": "Korea Republic of", "FLAG": "https://raw.githubusercontent.com/FreeSSTP/server-list/main/flags/KR.png", "PING": "31 ms", "PORT": 1521, "UPTIME": "8 days", "SESSIONS": 76, "LINE_QUALITY": "224.57 Mbps", "SCORE": 1413657}, {"HOSTNAME": "vpn926729611.opengw.net", "LOCATION": "Korea Republic of", "FLAG": "https://raw.githubusercontent.com/FreeSSTP/server-list/main/flags/KR.png", "PING": "30 ms", "PORT": 1628, "UPTIME": "10 days", "SESSIONS": 61, "LINE_QUALITY": "76.93 Mbps", "SCORE": 1383947}, {"HOSTNAME": "vpn387645435.opengw.net", "LOCATION": "Korea Republic of", "FLAG": "https://raw.githubusercontent.com/FreeSSTP/server-list/main/flags/KR.png", "PING": "38 ms", "PORT": 1343, "UPTIME": "16 days", "SESSIONS": 13, "LINE_QUALITY": "85.23 Mbps", "SCORE": 1366963}, {"HOSTNAME": "2i6.opengw.net", "LOCATION": "Japan", "FLAG": "https://raw.githubusercontent.com/FreeSSTP/server-list/main/flags/JP.png", "PING": "34 ms", "PORT": 1194, "UPTIME": "7 days", "SESSIONS": 219, "LINE_QUALITY": "50.57 Mbps", "SCORE": 1346379}, {"HOSTNAME": "public-vpn-237.opengw.net", "LOCATION": "Japan", "FLAG": "https://raw.githubusercontent.com/FreeSSTP/server-list/main/flags/JP.png", "PING": "26 ms", "PORT": 443, "UPTIME": "17 days", "SESSIONS": 166, "LINE_QUALITY": "46.66 Mbps", "SCORE": 1328729}, {"HOSTNAME": "vpn989123917.opengw.net", "LOCATION": "Korea Republic of", "FLAG": "https://raw.githubusercontent.com/FreeSSTP/server-list/main/flags/KR.png", "PING": "25 ms", "PORT": 995, "UPTIME": "5 days", "SESSIONS": 55, "LINE_QUALITY": "93.18 Mbps", "SCORE": 1244820}, {"HOSTNAME": "public-vpn-245.opengw.net", "LOCATION": "Japan", "FLAG": "https://raw.githubusercontent.com/FreeSSTP/server-list/main/flags/JP.png", "PING": "22 ms", "PORT": 443, "UPTIME": "17 days", "SESSIONS": 41, "LINE_QUALITY": "253.23 Mbps", "SCORE": 1208793}, {"HOSTNAME": "vpn229128702.opengw.net", "LOCATION": "United States", "FLAG": "https://raw.githubusercontent.com/FreeSSTP/server-list/main/flags/US.png", "PING": "10 ms", "PORT": 443, "UPTIME": "10 days", "SESSIONS": 53, "LINE_QUALITY": "151.71 Mbps", "SCORE": 1182820}, {"HOSTNAME": "vpn207341522.opengw.net", "LOCATION": "Japan", "FLAG": "https://raw.githubusercontent.com/FreeSSTP/server-list/main/flags/JP.png", "PING": "1207 ms", "PORT": 1660, "UPTIME": "28 days", "SESSIONS": 102, "LINE_QUALITY": "13.47 Mbps", "SCORE": 1141487}, {"HOSTNAME": "opengw.opengw.net", "LOCATION": "Romania", "FLAG": "https://raw.githubusercontent.com/FreeSSTP/server-list/main/flags/RO.png", "PING": "6 ms", "PORT": 443, "UPTIME": "6 days", "SESSIONS": 415, "LINE_QUALITY": "325.40 Mbps", "SCORE": 1112362}, {"HOSTNAME": "vpn596148100.opengw.net", "LOCATION": "Japan", "FLAG": "https://raw.githubusercontent.com/FreeSSTP/server-list/main/flags/JP.png", "PING": "17 ms", "PORT": 1327, "UPTIME": "2 days", "SESSIONS": 34, "LINE_QUALITY": "58.04 Mbps", "SCORE": 932281}, {"HOSTNAME": "vpn815142268.opengw.net", "LOCATION": "Japan", "FLAG": "https://raw.githubusercontent.com/FreeSSTP/server-list/main/flags/JP.png", "PING": "9 ms", "PORT": 1599, "UPTIME": "2 days", "SESSIONS": 33, "LINE_QUALITY": "49.49 Mbps", "SCORE": 912305}, {"HOSTNAME": "vpn163234511.opengw.net", "LOCATION": "Korea Republic of", "FLAG": "https://raw.githubusercontent.com/FreeSSTP/server-list/main/flags/KR.png", "PING": "29 ms", "PORT": 1774, "UPTIME": "2 days", "SESSIONS": 38, "LINE_QUALITY": "95.49 Mbps", "SCORE": 907849}, {"HOSTNAME": "vpn789653874.opengw.net", "LOCATION": "Korea Republic of", "FLAG": "https://raw.githubusercontent.com/FreeSSTP/server-list/main/flags/KR.png", "PING": "27 ms", "PORT": 995, "UPTIME": "2 days", "SESSIONS": 15, "LINE_QUALITY": "77.03 Mbps", "SCORE": 839368}, {"HOSTNAME": "vpn967031725.opengw.net", "LOCATION": "Korea Republic of", "FLAG": "https://raw.githubusercontent.com/FreeSSTP/server-list/main/flags/KR.png", "PING": "29 ms", "PORT": 995, "UPTIME": "2 days", "SESSIONS": 15, "LINE_QUALITY": "54.47 Mbps", "SCORE": 824618}, {"HOSTNAME": "vpn362333064.opengw.net", "LOCATION": "Japan", "FLAG": "https://raw.githubusercontent.com/FreeSSTP/server-list/main/flags/JP.png", "PING": "7 ms", "PORT": 1276, "UPTIME": "1 days", "SESSIONS": 68, "LINE_QUALITY": "492.94 Mbps", "SCORE": 823431}, {"HOSTNAME": "vpn124639907.opengw.net", "LOCATION": "Japan", "FLAG": "https://raw.githubusercontent.com/FreeSSTP/server-list/main/flags/JP.png", "PING": "17 ms", "PORT": 1834, "UPTIME": "1 days", "SESSIONS": 30, "LINE_QUALITY": "190.13 Mbps", "SCORE": 807595}, {"HOSTNAME": "vpn236805446.opengw.net", "LOCATION": "Japan", "FLAG": "https://raw.githubusercontent.com/FreeSSTP/server-list/main/flags/JP.png", "PING": "5 ms", "PORT": 1853, "UPTIME": "23 hours", "SESSIONS": 27, "LINE_QUALITY": "2,071.52 Mbps", "SCORE": 792209}, {"HOSTNAME": "vpn468592520.opengw.net", "LOCATION": "Japan", "FLAG": "https://raw.githubusercontent.com/FreeSSTP/server-list/main/flags/JP.png", "PING": "1 ms", "PORT": 1324, "UPTIME": "23 hours", "SESSIONS": 47, "LINE_QUALITY": "888.01 Mbps", "SCORE": 791955}, {"HOSTNAME": "vpn955178337.opengw.net", "LOCATION": "Japan", "FLAG": "https://raw.githubusercontent.com/FreeSSTP/server-list/main/flags/JP.png", "PING": "2 ms", "PORT": 1483, "UPTIME": "23 hours", "SESSIONS": 28, "LINE_QUALITY": "502.54 Mbps", "SCORE": 773464}, {"HOSTNAME": "vpn118191394.opengw.net", "LOCATION": "Korea Republic of", "FLAG": "https://raw.githubusercontent.com/FreeSSTP/server-list/main/flags/KR.png", "PING": "25 ms", "PORT": 995, "UPTIME": "23 hours", "SESSIONS": 13, "LINE_QUALITY": "289.68 Mbps", "SCORE": 708817}, {"HOSTNAME": "vpn526900542.opengw.net", "LOCATION": "Korea Republic of", "FLAG": "https://raw.githubusercontent.com/FreeSSTP/server-list/main/flags/KR.png", "PING": "31 ms", "PORT": 1453, "UPTIME": "1 days", "SESSIONS": 11, "LINE_QUALITY": "69.66 Mbps", "SCORE": 707361}, {"HOSTNAME": "vpn735209276.opengw.net", "LOCATION": "Korea Republic of", "FLAG": "https://raw.githubusercontent.com/FreeSSTP/server-list/main/flags/KR.png", "PING": "27 ms", "PORT": 443, "UPTIME": "23 hours", "SESSIONS": 159, "LINE_QUALITY": "308.11 Mbps", "SCORE": 703433}, {"HOSTNAME": "vpn798499733.opengw.net", "LOCATION": "Japan", "FLAG": "https://raw.githubusercontent.com/FreeSSTP/server-list/main/flags/JP.png", "PING": "16 ms", "PORT": 1605, "UPTIME": "6 hours", "SESSIONS": 61, "LINE_QUALITY": "720.28 Mbps", "SCORE": 695513}, {"HOSTNAME": "vpn509832165.opengw.net", "LOCATION": "Korea Republic of", "FLAG": "https://raw.githubusercontent.com/FreeSSTP/server-list/main/flags/KR.png", "PING": "31 ms", "PORT": 1994, "UPTIME": "1 days", "SESSIONS": 17, "LINE_QUALITY": "77.80 Mbps", "SCORE": 683940}, {"HOSTNAME": "vpn710866893.opengw.net", "LOCATION": "Korea Republic of", "FLAG": "https://raw.githubusercontent.com/FreeSSTP/server-list/main/flags/KR.png", "PING": "29 ms", "PORT": 443, "UPTIME": "9 hours", "SESSIONS": 86, "LINE_QUALITY": "51.07 Mbps", "SCORE": 658678}, {"HOSTNAME": "vpn438625619.opengw.net", "LOCATION": "Japan", "FLAG": "https://raw.githubusercontent.com/FreeSSTP/server-list/main/flags/JP.png", "PING": "4 ms", "PORT": 1843, "UPTIME": "3 hours", "SESSIONS": 3, "LINE_QUALITY": "627.56 Mbps", "SCORE": 658678}, {"HOSTNAME": "vpn680583464.opengw.net", "LOCATION": "Japan", "FLAG": "https://raw.githubusercontent.com/FreeSSTP/server-list/main/flags/JP.png", "PING": "2 ms", "PORT": 1958, "UPTIME": "0 mins", "SESSIONS": 5, "LINE_QUALITY": "66.49 Mbps", "SCORE": 652013}, {"HOSTNAME": "vpn471659883.opengw.net", "LOCATION": "Japan", "FLAG": "https://raw.githubusercontent.com/FreeSSTP/server-list/main/flags/JP.png", "PING": "6 ms", "PORT": 1718, "UPTIME": "6 hours", "SESSIONS": 12, "LINE_QUALITY": "245.57 Mbps", "SCORE": 651985}, {"HOSTNAME": "vpn901722321.opengw.net", "LOCATION": "Korea Republic of", "FLAG": "https://raw.githubusercontent.com/FreeSSTP/server-list/main/flags/KR.png", "PING": "38 ms", "PORT": 1538, "UPTIME": "1 days", "SESSIONS": 8, "LINE_QUALITY": "94.66 Mbps", "SCORE": 650538}, {"HOSTNAME": "vpn934833397.opengw.net", "LOCATION": "Japan", "FLAG": "https://raw.githubusercontent.com/FreeSSTP/server-list/main/flags/JP.png", "PING": "16 ms", "PORT": 1383, "UPTIME": "3 hours", "SESSIONS": 8, "LINE_QUALITY": "93.61 Mbps", "SCORE": 646182}, {"HOSTNAME": "vpn653156583.opengw.net", "LOCATION": "Korea Republic of", "FLAG": "https://raw.githubusercontent.com/FreeSSTP/server-list/main/flags/KR.png", "PING": "30 ms", "PORT": 1414, "UPTIME": "23 hours", "SESSIONS": 10, "LINE_QUALITY": "479.79 Mbps", "SCORE": 641673}, {"HOSTNAME": "vpn565032756.opengw.net", "LOCATION": "Thailand", "FLAG": "https://raw.githubusercontent.com/FreeSSTP/server-list/main/flags/TH.png", "PING": "26 ms", "PORT": 1353, "UPTIME": "9 hours", "SESSIONS": 0, "LINE_QUALITY": "470.08 Mbps", "SCORE": 638302}, {"HOSTNAME": "vpn863578814.opengw.net", "LOCATION": "Japan", "FLAG": "https://raw.githubusercontent.com/FreeSSTP/server-list/main/flags/JP.png", "PING": "2 ms", "PORT": 1759, "UPTIME": "0 mins", "SESSIONS": 21, "LINE_QUALITY": "971.44 Mbps", "SCORE": 638282}, {"HOSTNAME": "vpn314972559.opengw.net", "LOCATION": "Japan", "FLAG": "https://raw.githubusercontent.com/FreeSSTP/server-list/main/flags/JP.png", "PING": "3 ms", "PORT": 1600, "UPTIME": "0 mins", "SESSIONS": 11, "LINE_QUALITY": "885.42 Mbps", "SCORE": 638122}, {"HOSTNAME": "vpn332071461.opengw.net", "LOCATION": "Japan", "FLAG": "https://raw.githubusercontent.com/FreeSSTP/server-list/main/flags/JP.png", "PING": "9 ms", "PORT": 1444, "UPTIME": "3 hours", "SESSIONS": 0, "LINE_QUALITY": "179.68 Mbps", "SCORE": 632446}, {"HOSTNAME": "vpn633986249.opengw.net", "LOCATION": "Japan", "FLAG": "https://raw.githubusercontent.com/FreeSSTP/server-list/main/flags/JP.png", "PING": "4 ms", "PORT": 1280, "UPTIME": "6 hours", "SESSIONS": 17, "LINE_QUALITY": "97.13 Mbps", "SCORE": 629512}, {"HOSTNAME": "vpn838674243.opengw.net", "LOCATION": "Japan", "FLAG": "https://raw.githubusercontent.com/FreeSSTP/server-list/main/flags/JP.png", "PING": "7 ms", "PORT": 1671, "UPTIME": "0 mins", "SESSIONS": 6, "LINE_QUALITY": "78.67 Mbps", "SCORE": 629008}, {"HOSTNAME": "vpn163012412.opengw.net", "LOCATION": "Hong Kong", "FLAG": "https://raw.githubusercontent.com/FreeSSTP/server-list/main/flags/HK.png", "PING": "2 ms", "PORT": 1435, "UPTIME": "3 hours", "SESSIONS": 18, "LINE_QUALITY": "203.52 Mbps", "SCORE": 628798}, {"HOSTNAME": "vpn964804975.opengw.net", "LOCATION": "Japan", "FLAG": "https://raw.githubusercontent.com/FreeSSTP/server-list/main/flags/JP.png", "PING": "2 ms", "PORT": 1587, "UPTIME": "0 mins", "SESSIONS": 11, "LINE_QUALITY": "371.05 Mbps", "SCORE": 626820}, {"HOSTNAME": "vpn484609025.opengw.net", "LOCATION": "Korea Republic of", "FLAG": "https://raw.githubusercontent.com/FreeSSTP/server-list/main/flags/KR.png", "PING": "27 ms", "PORT": 1704, "UPTIME": "6 hours", "SESSIONS": 4, "LINE_QUALITY": "110.64 Mbps", "SCORE": 620249}, {"HOSTNAME": "vpn187146444.opengw.net", "LOCATION": "Japan", "FLAG": "https://raw.githubusercontent.com/FreeSSTP/server-list/main/flags/JP.png", "PING": "7 ms", "PORT": 1642, "UPTIME": "0 mins", "SESSIONS": 11, "LINE_QUALITY": "87.84 Mbps", "SCORE": 617975}, {"HOSTNAME": "vpn100393288.opengw.net", "LOCATION": "Japan", "FLAG": "https://raw.githubusercontent.com/FreeSSTP/server-list/main/flags/JP.png", "PING": "9 ms", "PORT": 1998, "UPTIME": "3 hours", "SESSIONS": 7, "LINE_QUALITY": "277.60 Mbps", "SCORE": 609899}, {"HOSTNAME": "vpn623845864.opengw.net", "LOCATION": "Korea Republic of", "FLAG": "https://raw.githubusercontent.com/FreeSSTP/server-list/main/flags/KR.png", "PING": "33 ms", "PORT": 1410, "UPTIME": "9 hours", "SESSIONS": 3, "LINE_QUALITY": "88.95 Mbps", "SCORE": 606557}, {"HOSTNAME": "vpn562457128.opengw.net", "LOCATION": "Korea Republic of", "FLAG": "https://raw.githubusercontent.com/FreeSSTP/server-list/main/flags/KR.png", "PING": "31 ms", "PORT": 995, "UPTIME": "6 hours", "SESSIONS": 8, "LINE_QUALITY": "200.61 Mbps", "SCORE": 603355}, {"HOSTNAME": "vpn493271266.opengw.net", "LOCATION": "Korea Republic of", "FLAG": "https://raw.githubusercontent.com/FreeSSTP/server-list/main/flags/KR.png", "PING": "29 ms", "PORT": 995, "UPTIME": "3 hours", "SESSIONS": 5, "LINE_QUALITY": "265.31 Mbps", "SCORE": 595882}, {"HOSTNAME": "vpn743879810.opengw.net", "LOCATION": "Korea Republic of", "FLAG": "https://raw.githubusercontent.com/FreeSSTP/server-list/main/flags/KR.png", "PING": "31 ms", "PORT": 995, "UPTIME": "6 hours", "SESSIONS": 1, "LINE_QUALITY": "468.70 Mbps", "SCORE": 594842}, {"HOSTNAME": "vpn892395043.opengw.net", "LOCATION": "Japan", "FLAG": "https://raw.githubusercontent.com/FreeSSTP/server-list/main/flags/JP.png", "PING": "4 ms", "PORT": 1620, "UPTIME": "0 mins", "SESSIONS": 3, "LINE_QUALITY": "293.82 Mbps", "SCORE": 594132}, {"HOSTNAME": "vpn223516252.opengw.net", "LOCATION": "Japan", "FLAG": "https://raw.githubusercontent.com/FreeSSTP/server-list/main/flags/JP.png", "PING": "16 ms", "PORT": 1346, "UPTIME": "23 hours", "SESSIONS": 11, "LINE_QUALITY": "19.11 Mbps", "SCORE": 592403}, {"HOSTNAME": "vpn158020334.opengw.net", "LOCATION": "Korea Republic of", "FLAG": "https://raw.githubusercontent.com/FreeSSTP/server-list/main/flags/KR.png", "PING": "31 ms", "PORT": 1263, "UPTIME": "6 hours", "SESSIONS": 8, "LINE_QUALITY": "311.79 Mbps", "SCORE": 586316}, {"HOSTNAME": "vpn339723621.opengw.net", "LOCATION": "Korea Republic of", "FLAG": "https://raw.githubusercontent.com/FreeSSTP/server-list/main/flags/KR.png", "PING": "30 ms", "PORT": 995, "UPTIME": "3 hours", "SESSIONS": 12, "LINE_QUALITY": "92.52 Mbps", "SCORE": 584177}, {"HOSTNAME": "vpn356610980.opengw.net", "LOCATION": "Korea Republic of", "FLAG": "https://raw.githubusercontent.com/FreeSSTP/server-list/main/flags/KR.png", "PING": "33 ms", "PORT": 1692, "UPTIME": "3 hours", "SESSIONS": 9, "LINE_QUALITY": "95.51 Mbps", "SCORE": 583555}, {"HOSTNAME": "vpn723384853.opengw.net", "LOCATION": "Korea Republic of", "FLAG": "https://raw.githubusercontent.com/FreeSSTP/server-list/main/flags/KR.png", "PING": "34 ms", "PORT": 1457, "UPTIME": "9 hours", "SESSIONS": 12, "LINE_QUALITY": "222.32 Mbps", "SCORE": 582168}, {"HOSTNAME": "vpn387855693.opengw.net", "LOCATION": "Korea Republic of", "FLAG": "https://raw.githubusercontent.com/FreeSSTP/server-list/main/flags/KR.png", "PING": "33 ms", "PORT": 995, "UPTIME": "9 hours", "SESSIONS": 11, "LINE_QUALITY": "100.50 Mbps", "SCORE": 578554}, {"HOSTNAME": "vpn315958956.opengw.net", "LOCATION": "Korea Republic of", "FLAG": "https://raw.githubusercontent.com/FreeSSTP/server-list/main/flags/KR.png", "PING": "30 ms", "PORT": 995, "UPTIME": "0 mins", "SESSIONS": 4, "LINE_QUALITY": "286.86 Mbps", "SCORE": 576410}, {"HOSTNAME": "vpn830947195.opengw.net", "LOCATION": "Korea Republic of", "FLAG": "https://raw.githubusercontent.com/FreeSSTP/server-list/main/flags/KR.png", "PING": "33 ms", "PORT": 1321, "UPTIME": "0 mins", "SESSIONS": 3, "LINE_QUALITY": "80.01 Mbps", "SCORE": 565339}, {"HOSTNAME": "vpn189786916.opengw.net", "LOCATION": "Korea Republic of", "FLAG": "https://raw.githubusercontent.com/FreeSSTP/server-list/main/flags/KR.png", "PING": "30 ms", "PORT": 995, "UPTIME": "3 hours", "SESSIONS": 4, "LINE_QUALITY": "305.99 Mbps", "SCORE": 545633}, {"HOSTNAME": "vpn290567323.opengw.net", "LOCATION": "Korea Republic of", "FLAG": "https://raw.githubusercontent.com/FreeSSTP/server-list/main/flags/KR.png", "PING": "31 ms", "PORT": 1376, "UPTIME": "0 mins", "SESSIONS": 0, "LINE_QUALITY": "95.08 Mbps", "SCORE": 542972}, {"HOSTNAME": "vpn219890371.opengw.net", "LOCATION": "Korea Republic of", "FLAG": "https://raw.githubusercontent.com/FreeSSTP/server-list/main/flags/KR.png", "PING": "34 ms", "PORT": 1917, "UPTIME": "0 mins", "SESSIONS": 7, "LINE_QUALITY": "91.82 Mbps", "SCORE": 541988}, {"HOSTNAME": "vpn794921480.opengw.net", "LOCATION": "Korea Republic of", "FLAG": "https://raw.githubusercontent.com/FreeSSTP/server-list/main/flags/KR.png", "PING": "32 ms", "PORT": 1386, "UPTIME": "0 mins", "SESSIONS": 1, "LINE_QUALITY": "285.13 Mbps", "SCORE": 535899}, {"HOSTNAME": "vpn645881192.opengw.net", "LOCATION": "Korea Republic of", "FLAG": "https://raw.githubusercontent.com/FreeSSTP/server-list/main/flags/KR.png", "PING": "32 ms", "PORT": 1857, "UPTIME": "0 mins", "SESSIONS": 4, "LINE_QUALITY": "355.72 Mbps", "SCORE": 533748}, {"HOSTNAME": "vpn480196781.opengw.net", "LOCATION": "Korea Republic of", "FLAG": "https://raw.githubusercontent.com/FreeSSTP/server-list/main/flags/KR.png", "PING": "31 ms", "PORT": 995, "UPTIME": "0 mins", "SESSIONS": 4, "LINE_QUALITY": "243.04 Mbps", "SCORE": 531853}, {"HOSTNAME": "vpn286473696.opengw.net", "LOCATION": "Korea Republic of", "FLAG": "https://raw.githubusercontent.com/FreeSSTP/server-list/main/flags/KR.png", "PING": "29 ms", "PORT": 995, "UPTIME": "0 mins", "SESSIONS": 2, "LINE_QUALITY": "598.89 Mbps", "SCORE": 527430}, {"HOSTNAME": "vpn313104371.opengw.net", "LOCATION": "Japan", "FLAG": "https://raw.githubusercontent.com/FreeSSTP/server-list/main/flags/JP.png", "PING": "54 ms", "PORT": 1519, "UPTIME": "6 hours", "SESSIONS": 2, "LINE_QUALITY": "74.73 Mbps", "SCORE": 525608}, {"HOSTNAME": "vpn139013599.opengw.net", "LOCATION": "Japan", "FLAG": "https://raw.githubusercontent.com/FreeSSTP/server-list/main/flags/JP.png", "PING": "55 ms", "PORT": 1484, "UPTIME": "3 hours", "SESSIONS": 14, "LINE_QUALITY": "39.97 Mbps", "SCORE": 504938}, {"HOSTNAME": "vpn902030343.opengw.net", "LOCATION": "Russian Federation", "FLAG": "https://raw.githubusercontent.com/FreeSSTP/server-list/main/flags/RU.png", "PING": "-", "PORT": 1337, "UPTIME": "3 hours", "SESSIONS": 0, "LINE_QUALITY": "50.46 Mbps", "SCORE": 443078}, {"HOSTNAME": "vpn541516872.opengw.net", "LOCATION": "Japan", "FLAG": "https://raw.githubusercontent.com/FreeSSTP/server-list/main/flags/JP.png", "PING": "-", "PORT": 1575, "UPTIME": "6 hours", "SESSIONS": 4, "LINE_QUALITY": "81.55 Mbps", "SCORE": 434426}, {"HOSTNAME": "vpn137393230.opengw.net", "LOCATION": "Korea Republic of", "FLAG": "https://raw.githubusercontent.com/FreeSSTP/server-list/main/flags/KR.png", "PING": "-", "PORT": 995, "UPTIME": "0 mins", "SESSIONS": 2, "LINE_QUALITY": "474.61 Mbps", "SCORE": 410624}]