[{"HOSTNAME": "public-vpn-251.opengw.net", "LOCATION": "Japan", "FLAG": "https://raw.githubusercontent.com/FreeSSTP/server-list/main/flags/JP.png", "PING": "9 ms", "PORT": 443, "UPTIME": "11 days", "SESSIONS": 355, "LINE_QUALITY": "509.41 Mbps", "SCORE": 2435165}, {"HOSTNAME": "public-vpn-71.opengw.net", "LOCATION": "Japan", "FLAG": "https://raw.githubusercontent.com/FreeSSTP/server-list/main/flags/JP.png", "PING": "24 ms", "PORT": 443, "UPTIME": "11 days", "SESSIONS": 215, "LINE_QUALITY": "1,600.85 Mbps", "SCORE": 2359503}, {"HOSTNAME": "public-vpn-241.opengw.net", "LOCATION": "Japan", "FLAG": "https://raw.githubusercontent.com/FreeSSTP/server-list/main/flags/JP.png", "PING": "12 ms", "PORT": 443, "UPTIME": "11 days", "SESSIONS": 286, "LINE_QUALITY": "1,742.97 Mbps", "SCORE": 2220355}, {"HOSTNAME": "public-vpn-246.opengw.net", "LOCATION": "Japan", "FLAG": "https://raw.githubusercontent.com/FreeSSTP/server-list/main/flags/JP.png", "PING": "13 ms", "PORT": 443, "UPTIME": "11 days", "SESSIONS": 188, "LINE_QUALITY": "990.81 Mbps", "SCORE": 2043336}, {"HOSTNAME": "public-vpn-215.opengw.net", "LOCATION": "Japan", "FLAG": "https://raw.githubusercontent.com/FreeSSTP/server-list/main/flags/JP.png", "PING": "13 ms", "PORT": 443, "UPTIME": "11 days", "SESSIONS": 176, "LINE_QUALITY": "447.18 Mbps", "SCORE": 1882262}, {"HOSTNAME": "public-vpn-48.opengw.net", "LOCATION": "Japan", "FLAG": "https://raw.githubusercontent.com/FreeSSTP/server-list/main/flags/JP.png", "PING": "15 ms", "PORT": 443, "UPTIME": "11 days", "SESSIONS": 286, "LINE_QUALITY": "426.25 Mbps", "SCORE": 1684258}, {"HOSTNAME": "public-vpn-65.opengw.net", "LOCATION": "Japan", "FLAG": "https://raw.githubusercontent.com/FreeSSTP/server-list/main/flags/JP.png", "PING": "9 ms", "PORT": 443, "UPTIME": "11 days", "SESSIONS": 300, "LINE_QUALITY": "635.96 Mbps", "SCORE": 1663348}, {"HOSTNAME": "public-vpn-158.opengw.net", "LOCATION": "Japan", "FLAG": "https://raw.githubusercontent.com/FreeSSTP/server-list/main/flags/JP.png", "PING": "20 ms", "PORT": 443, "UPTIME": "11 days", "SESSIONS": 197, "LINE_QUALITY": "842.41 Mbps", "SCORE": 1659234}, {"HOSTNAME": "vpn485113366.opengw.net", "LOCATION": "Japan", "FLAG": "https://raw.githubusercontent.com/FreeSSTP/server-list/main/flags/JP.png", "PING": "12 ms", "PORT": 1291, "UPTIME": "19 days", "SESSIONS": 72, "LINE_QUALITY": "209.39 Mbps", "SCORE": 1547894}, {"HOSTNAME": "public-vpn-55.opengw.net", "LOCATION": "Japan", "FLAG": "https://raw.githubusercontent.com/FreeSSTP/server-list/main/flags/JP.png", "PING": "9 ms", "PORT": 443, "UPTIME": "11 days", "SESSIONS": 200, "LINE_QUALITY": "1,345.19 Mbps", "SCORE": 1545074}, {"HOSTNAME": "vpn642064018.opengw.net", "LOCATION": "Japan", "FLAG": "https://raw.githubusercontent.com/FreeSSTP/server-list/main/flags/JP.png", "PING": "10 ms", "PORT": 1836, "UPTIME": "13 days", "SESSIONS": 66, "LINE_QUALITY": "186.45 Mbps", "SCORE": 1539631}, {"HOSTNAME": "vpn168022047.opengw.net", "LOCATION": "Japan", "FLAG": "https://raw.githubusercontent.com/FreeSSTP/server-list/main/flags/JP.png", "PING": "8 ms", "PORT": 1214, "UPTIME": "20 days", "SESSIONS": 45, "LINE_QUALITY": "78.78 Mbps", "SCORE": 1519739}, {"HOSTNAME": "vpn491169900.opengw.net", "LOCATION": "Japan", "FLAG": "https://raw.githubusercontent.com/FreeSSTP/server-list/main/flags/JP.png", "PING": "10 ms", "PORT": 1916, "UPTIME": "22 days", "SESSIONS": 77, "LINE_QUALITY": "455.93 Mbps", "SCORE": 1489351}, {"HOSTNAME": "vpn812677596.opengw.net", "LOCATION": "Korea Republic of", "FLAG": "https://raw.githubusercontent.com/FreeSSTP/server-list/main/flags/KR.png", "PING": "26 ms", "PORT": 995, "UPTIME": "61 days", "SESSIONS": 80, "LINE_QUALITY": "70.54 Mbps", "SCORE": 1478397}, {"HOSTNAME": "vpn324168628.opengw.net", "LOCATION": "Korea Republic of", "FLAG": "https://raw.githubusercontent.com/FreeSSTP/server-list/main/flags/KR.png", "PING": "31 ms", "PORT": 995, "UPTIME": "12 days", "SESSIONS": 76, "LINE_QUALITY": "29.46 Mbps", "SCORE": 1462404}, {"HOSTNAME": "public-vpn-126.opengw.net", "LOCATION": "Japan", "FLAG": "https://raw.githubusercontent.com/FreeSSTP/server-list/main/flags/JP.png", "PING": "27 ms", "PORT": 443, "UPTIME": "11 days", "SESSIONS": 128, "LINE_QUALITY": "1,897.65 Mbps", "SCORE": 1460090}, {"HOSTNAME": "vpn676385833.opengw.net", "LOCATION": "Korea Republic of", "FLAG": "https://raw.githubusercontent.com/FreeSSTP/server-list/main/flags/KR.png", "PING": "35 ms", "PORT": 1452, "UPTIME": "7 days", "SESSIONS": 72, "LINE_QUALITY": "432.64 Mbps", "SCORE": 1451318}, {"HOSTNAME": "vpn105048124.opengw.net", "LOCATION": "Korea Republic of", "FLAG": "https://raw.githubusercontent.com/FreeSSTP/server-list/main/flags/KR.png", "PING": "30 ms", "PORT": 1811, "UPTIME": "17 days", "SESSIONS": 79, "LINE_QUALITY": "297.73 Mbps", "SCORE": 1427986}, {"HOSTNAME": "vpn332918459.opengw.net", "LOCATION": "Korea Republic of", "FLAG": "https://raw.githubusercontent.com/FreeSSTP/server-list/main/flags/KR.png", "PING": "34 ms", "PORT": 995, "UPTIME": "33 days", "SESSIONS": 90, "LINE_QUALITY": "92.81 Mbps", "SCORE": 1422420}, {"HOSTNAME": "vpn611939217.opengw.net", "LOCATION": "Korea Republic of", "FLAG": "https://raw.githubusercontent.com/FreeSSTP/server-list/main/flags/KR.png", "PING": "32 ms", "PORT": 1579, "UPTIME": "6 days", "SESSIONS": 70, "LINE_QUALITY": "252.12 Mbps", "SCORE": 1412901}, {"HOSTNAME": "vpn306389621.opengw.net", "LOCATION": "Korea Republic of", "FLAG": "https://raw.githubusercontent.com/FreeSSTP/server-list/main/flags/KR.png", "PING": "31 ms", "PORT": 1494, "UPTIME": "10 days", "SESSIONS": 77, "LINE_QUALITY": "44.26 Mbps", "SCORE": 1402200}, {"HOSTNAME": "public-vpn-235.opengw.net", "LOCATION": "Japan", "FLAG": "https://raw.githubusercontent.com/FreeSSTP/server-list/main/flags/JP.png", "PING": "8 ms", "PORT": 443, "UPTIME": "11 days", "SESSIONS": 235, "LINE_QUALITY": "737.96 Mbps", "SCORE": 1388717}, {"HOSTNAME": "vpn264350121.opengw.net", "LOCATION": "Korea Republic of", "FLAG": "https://raw.githubusercontent.com/FreeSSTP/server-list/main/flags/KR.png", "PING": "30 ms", "PORT": 1934, "UPTIME": "10 days", "SESSIONS": 78, "LINE_QUALITY": "81.78 Mbps", "SCORE": 1381592}, {"HOSTNAME": "vpn893336882.opengw.net", "LOCATION": "Korea Republic of", "FLAG": "https://raw.githubusercontent.com/FreeSSTP/server-list/main/flags/KR.png", "PING": "65 ms", "PORT": 995, "UPTIME": "8 days", "SESSIONS": 72, "LINE_QUALITY": "80.94 Mbps", "SCORE": 1361470}, {"HOSTNAME": "vpn648453261.opengw.net", "LOCATION": "Korea Republic of", "FLAG": "https://raw.githubusercontent.com/FreeSSTP/server-list/main/flags/KR.png", "PING": "35 ms", "PORT": 1658, "UPTIME": "64 days", "SESSIONS": 78, "LINE_QUALITY": "33.27 Mbps", "SCORE": 1360706}, {"HOSTNAME": "vpn552152606.opengw.net", "LOCATION": "Cambodia", "FLAG": "https://raw.githubusercontent.com/FreeSSTP/server-list/main/flags/KH.png", "PING": "27 ms", "PORT": 1416, "UPTIME": "11 days", "SESSIONS": 69, "LINE_QUALITY": "24.27 Mbps", "SCORE": 1349243}, {"HOSTNAME": "public-vpn-165.opengw.net", "LOCATION": "Japan", "FLAG": "https://raw.githubusercontent.com/FreeSSTP/server-list/main/flags/JP.png", "PING": "22 ms", "PORT": 443, "UPTIME": "11 days", "SESSIONS": 205, "LINE_QUALITY": "1,442.16 Mbps", "SCORE": 1332886}, {"HOSTNAME": "opengw.opengw.net", "LOCATION": "Romania", "FLAG": "https://raw.githubusercontent.com/FreeSSTP/server-list/main/flags/RO.png", "PING": "5 ms", "PORT": 443, "UPTIME": "82 days", "SESSIONS": 383, "LINE_QUALITY": "567.67 Mbps", "SCORE": 1220559}, {"HOSTNAME": "vpn947314188.opengw.net", "LOCATION": "Korea Republic of", "FLAG": "https://raw.githubusercontent.com/FreeSSTP/server-list/main/flags/KR.png", "PING": "28 ms", "PORT": 995, "UPTIME": "4 days", "SESSIONS": 73, "LINE_QUALITY": "91.44 Mbps", "SCORE": 1121413}, {"HOSTNAME": "vpn134916986.opengw.net", "LOCATION": "Korea Republic of", "FLAG": "https://raw.githubusercontent.com/FreeSSTP/server-list/main/flags/KR.png", "PING": "28 ms", "PORT": 995, "UPTIME": "4 days", "SESSIONS": 4, "LINE_QUALITY": "150.52 Mbps", "SCORE": 1116243}, {"HOSTNAME": "vpn698252028.opengw.net", "LOCATION": "Japan", "FLAG": "https://raw.githubusercontent.com/FreeSSTP/server-list/main/flags/JP.png", "PING": "4 ms", "PORT": 1970, "UPTIME": "3 days", "SESSIONS": 63, "LINE_QUALITY": "451.45 Mbps", "SCORE": 1086191}, {"HOSTNAME": "vpn185092294.opengw.net", "LOCATION": "Korea Republic of", "FLAG": "https://raw.githubusercontent.com/FreeSSTP/server-list/main/flags/KR.png", "PING": "34 ms", "PORT": 995, "UPTIME": "6 days", "SESSIONS": 35, "LINE_QUALITY": "4.65 Mbps", "SCORE": 1014597}, {"HOSTNAME": "vpn399654655.opengw.net", "LOCATION": "Japan", "FLAG": "https://raw.githubusercontent.com/FreeSSTP/server-list/main/flags/JP.png", "PING": "15 ms", "PORT": 1962, "UPTIME": "2 days", "SESSIONS": 33, "LINE_QUALITY": "94.23 Mbps", "SCORE": 992813}, {"HOSTNAME": "vpn489256853.opengw.net", "LOCATION": "Japan", "FLAG": "https://raw.githubusercontent.com/FreeSSTP/server-list/main/flags/JP.png", "PING": "9 ms", "PORT": 1642, "UPTIME": "2 days", "SESSIONS": 79, "LINE_QUALITY": "608.18 Mbps", "SCORE": 980487}, {"HOSTNAME": "vpn702361566.opengw.net", "LOCATION": "Korea Republic of", "FLAG": "https://raw.githubusercontent.com/FreeSSTP/server-list/main/flags/KR.png", "PING": "37 ms", "PORT": 1677, "UPTIME": "3 days", "SESSIONS": 61, "LINE_QUALITY": "91.13 Mbps", "SCORE": 976311}, {"HOSTNAME": "vpn828600309.opengw.net", "LOCATION": "Korea Republic of", "FLAG": "https://raw.githubusercontent.com/FreeSSTP/server-list/main/flags/KR.png", "PING": "27 ms", "PORT": 995, "UPTIME": "3 days", "SESSIONS": 67, "LINE_QUALITY": "415.33 Mbps", "SCORE": 961845}, {"HOSTNAME": "vpn733362618.opengw.net", "LOCATION": "Korea Republic of", "FLAG": "https://raw.githubusercontent.com/FreeSSTP/server-list/main/flags/KR.png", "PING": "30 ms", "PORT": 1497, "UPTIME": "2 days", "SESSIONS": 3, "LINE_QUALITY": "445.56 Mbps", "SCORE": 897653}, {"HOSTNAME": "vpn561892346.opengw.net", "LOCATION": "Japan", "FLAG": "https://raw.githubusercontent.com/FreeSSTP/server-list/main/flags/JP.png", "PING": "1 ms", "PORT": 1931, "UPTIME": "2 days", "SESSIONS": 74, "LINE_QUALITY": "520.63 Mbps", "SCORE": 891944}, {"HOSTNAME": "vpn788502559.opengw.net", "LOCATION": "Japan", "FLAG": "https://raw.githubusercontent.com/FreeSSTP/server-list/main/flags/JP.png", "PING": "14 ms", "PORT": 1908, "UPTIME": "1 days", "SESSIONS": 52, "LINE_QUALITY": "290.71 Mbps", "SCORE": 859959}, {"HOSTNAME": "vpn346763354.opengw.net", "LOCATION": "Japan", "FLAG": "https://raw.githubusercontent.com/FreeSSTP/server-list/main/flags/JP.png", "PING": "4 ms", "PORT": 1944, "UPTIME": "1 days", "SESSIONS": 16, "LINE_QUALITY": "252.61 Mbps", "SCORE": 830519}, {"HOSTNAME": "vpn251634266.opengw.net", "LOCATION": "Japan", "FLAG": "https://raw.githubusercontent.com/FreeSSTP/server-list/main/flags/JP.png", "PING": "17 ms", "PORT": 1786, "UPTIME": "1 days", "SESSIONS": 12, "LINE_QUALITY": "264.80 Mbps", "SCORE": 782220}, {"HOSTNAME": "vpn974719727.opengw.net", "LOCATION": "Japan", "FLAG": "https://raw.githubusercontent.com/FreeSSTP/server-list/main/flags/JP.png", "PING": "6 ms", "PORT": 1717, "UPTIME": "1 days", "SESSIONS": 14, "LINE_QUALITY": "946.18 Mbps", "SCORE": 780759}, {"HOSTNAME": "vpn376421133.opengw.net", "LOCATION": "Japan", "FLAG": "https://raw.githubusercontent.com/FreeSSTP/server-list/main/flags/JP.png", "PING": "7 ms", "PORT": 1877, "UPTIME": "13 hours", "SESSIONS": 51, "LINE_QUALITY": "290.94 Mbps", "SCORE": 748423}, {"HOSTNAME": "vpn194170357.opengw.net", "LOCATION": "Malaysia", "FLAG": "https://raw.githubusercontent.com/FreeSSTP/server-list/main/flags/MY.png", "PING": "31 ms", "PORT": 443, "UPTIME": "1 days", "SESSIONS": 21, "LINE_QUALITY": "145.90 Mbps", "SCORE": 747406}, {"HOSTNAME": "vpn544949430.opengw.net", "LOCATION": "Korea Republic of", "FLAG": "https://raw.githubusercontent.com/FreeSSTP/server-list/main/flags/KR.png", "PING": "30 ms", "PORT": 995, "UPTIME": "1 days", "SESSIONS": 14, "LINE_QUALITY": "488.46 Mbps", "SCORE": 726629}, {"HOSTNAME": "vpn315523783.opengw.net", "LOCATION": "Japan", "FLAG": "https://raw.githubusercontent.com/FreeSSTP/server-list/main/flags/JP.png", "PING": "5 ms", "PORT": 1620, "UPTIME": "13 hours", "SESSIONS": 21, "LINE_QUALITY": "80.57 Mbps", "SCORE": 707299}, {"HOSTNAME": "vpn849621319.opengw.net", "LOCATION": "Korea Republic of", "FLAG": "https://raw.githubusercontent.com/FreeSSTP/server-list/main/flags/KR.png", "PING": "32 ms", "PORT": 995, "UPTIME": "1 days", "SESSIONS": 13, "LINE_QUALITY": "419.22 Mbps", "SCORE": 702611}, {"HOSTNAME": "vpn667861253.opengw.net", "LOCATION": "Japan", "FLAG": "https://raw.githubusercontent.com/FreeSSTP/server-list/main/flags/JP.png", "PING": "3 ms", "PORT": 1355, "UPTIME": "4 hours", "SESSIONS": 27, "LINE_QUALITY": "860.27 Mbps", "SCORE": 682015}, {"HOSTNAME": "vpn893007828.opengw.net", "LOCATION": "Indonesia", "FLAG": "https://raw.githubusercontent.com/FreeSSTP/server-list/main/flags/ID.png", "PING": "15 ms", "PORT": 1488, "UPTIME": "4 hours", "SESSIONS": 19, "LINE_QUALITY": "222.48 Mbps", "SCORE": 679401}, {"HOSTNAME": "vpn840886428.opengw.net", "LOCATION": "Japan", "FLAG": "https://raw.githubusercontent.com/FreeSSTP/server-list/main/flags/JP.png", "PING": "8 ms", "PORT": 1457, "UPTIME": "4 hours", "SESSIONS": 21, "LINE_QUALITY": "93.04 Mbps", "SCORE": 677273}, {"HOSTNAME": "vpn720962280.opengw.net", "LOCATION": "Japan", "FLAG": "https://raw.githubusercontent.com/FreeSSTP/server-list/main/flags/JP.png", "PING": "8 ms", "PORT": 1632, "UPTIME": "4 hours", "SESSIONS": 27, "LINE_QUALITY": "87.94 Mbps", "SCORE": 670083}, {"HOSTNAME": "vpn258515579.opengw.net", "LOCATION": "Hungary", "FLAG": "https://raw.githubusercontent.com/FreeSSTP/server-list/main/flags/HU.png", "PING": "15 ms", "PORT": 1928, "UPTIME": "4 hours", "SESSIONS": 11, "LINE_QUALITY": "166.16 Mbps", "SCORE": 666384}, {"HOSTNAME": "vpn409276817.opengw.net", "LOCATION": "Japan", "FLAG": "https://raw.githubusercontent.com/FreeSSTP/server-list/main/flags/JP.png", "PING": "13 ms", "PORT": 1416, "UPTIME": "8 hours", "SESSIONS": 0, "LINE_QUALITY": "77.43 Mbps", "SCORE": 662410}, {"HOSTNAME": "vpn915091479.opengw.net", "LOCATION": "Russian Federation", "FLAG": "https://raw.githubusercontent.com/FreeSSTP/server-list/main/flags/RU.png", "PING": "67 ms", "PORT": 1384, "UPTIME": "1 days", "SESSIONS": 16, "LINE_QUALITY": "96.36 Mbps", "SCORE": 658612}, {"HOSTNAME": "vpn633011388.opengw.net", "LOCATION": "Japan", "FLAG": "https://raw.githubusercontent.com/FreeSSTP/server-list/main/flags/JP.png", "PING": "2 ms", "PORT": 1209, "UPTIME": "4 hours", "SESSIONS": 4, "LINE_QUALITY": "692.48 Mbps", "SCORE": 656180}, {"HOSTNAME": "vpn451070640.opengw.net", "LOCATION": "Japan", "FLAG": "https://raw.githubusercontent.com/FreeSSTP/server-list/main/flags/JP.png", "PING": "3 ms", "PORT": 1362, "UPTIME": "4 hours", "SESSIONS": 31, "LINE_QUALITY": "407.23 Mbps", "SCORE": 650376}, {"HOSTNAME": "vpn665093769.opengw.net", "LOCATION": "Japan", "FLAG": "https://raw.githubusercontent.com/FreeSSTP/server-list/main/flags/JP.png", "PING": "6 ms", "PORT": 1965, "UPTIME": "4 hours", "SESSIONS": 7, "LINE_QUALITY": "294.45 Mbps", "SCORE": 641419}, {"HOSTNAME": "vpn134116042.opengw.net", "LOCATION": "Korea Republic of", "FLAG": "https://raw.githubusercontent.com/FreeSSTP/server-list/main/flags/KR.png", "PING": "128 ms", "PORT": 995, "UPTIME": "3 days", "SESSIONS": 60, "LINE_QUALITY": "9.23 Mbps", "SCORE": 640754}, {"HOSTNAME": "vpn838674243.opengw.net", "LOCATION": "Japan", "FLAG": "https://raw.githubusercontent.com/FreeSSTP/server-list/main/flags/JP.png", "PING": "5 ms", "PORT": 1671, "UPTIME": "4 hours", "SESSIONS": 17, "LINE_QUALITY": "91.49 Mbps", "SCORE": 634542}, {"HOSTNAME": "vpn381123125.opengw.net", "LOCATION": "Viet Nam", "FLAG": "https://raw.githubusercontent.com/FreeSSTP/server-list/main/flags/VN.png", "PING": "35 ms", "PORT": 1424, "UPTIME": "13 hours", "SESSIONS": 27, "LINE_QUALITY": "100.90 Mbps", "SCORE": 629479}, {"HOSTNAME": "vpn154698520.opengw.net", "LOCATION": "Japan", "FLAG": "https://raw.githubusercontent.com/FreeSSTP/server-list/main/flags/JP.png", "PING": "14 ms", "PORT": 1870, "UPTIME": "4 hours", "SESSIONS": 14, "LINE_QUALITY": "441.76 Mbps", "SCORE": 623339}, {"HOSTNAME": "vpn908820246.opengw.net", "LOCATION": "Canada", "FLAG": "https://raw.githubusercontent.com/FreeSSTP/server-list/main/flags/CA.png", "PING": "16 ms", "PORT": 1643, "UPTIME": "0 mins", "SESSIONS": 8, "LINE_QUALITY": "287.23 Mbps", "SCORE": 603676}, {"HOSTNAME": "vpn586421462.opengw.net", "LOCATION": "Japan", "FLAG": "https://raw.githubusercontent.com/FreeSSTP/server-list/main/flags/JP.png", "PING": "28 ms", "PORT": 1760, "UPTIME": "0 mins", "SESSIONS": 18, "LINE_QUALITY": "195.81 Mbps", "SCORE": 591855}, {"HOSTNAME": "vpn216324484.opengw.net", "LOCATION": "Korea Republic of", "FLAG": "https://raw.githubusercontent.com/FreeSSTP/server-list/main/flags/KR.png", "PING": "31 ms", "PORT": 995, "UPTIME": "8 hours", "SESSIONS": 12, "LINE_QUALITY": "63.07 Mbps", "SCORE": 585765}, {"HOSTNAME": "vpn676736646.opengw.net", "LOCATION": "Korea Republic of", "FLAG": "https://raw.githubusercontent.com/FreeSSTP/server-list/main/flags/KR.png", "PING": "31 ms", "PORT": 995, "UPTIME": "4 hours", "SESSIONS": 19, "LINE_QUALITY": "83.41 Mbps", "SCORE": 581020}, {"HOSTNAME": "vpn974630859.opengw.net", "LOCATION": "Russian Federation", "FLAG": "https://raw.githubusercontent.com/FreeSSTP/server-list/main/flags/RU.png", "PING": "51 ms", "PORT": 1299, "UPTIME": "13 hours", "SESSIONS": 0, "LINE_QUALITY": "45.11 Mbps", "SCORE": 580095}, {"HOSTNAME": "vpn276859183.opengw.net", "LOCATION": "Cambodia", "FLAG": "https://raw.githubusercontent.com/FreeSSTP/server-list/main/flags/KH.png", "PING": "30 ms", "PORT": 1978, "UPTIME": "0 mins", "SESSIONS": 6, "LINE_QUALITY": "81.63 Mbps", "SCORE": 579082}, {"HOSTNAME": "vpn884015740.opengw.net", "LOCATION": "Korea Republic of", "FLAG": "https://raw.githubusercontent.com/FreeSSTP/server-list/main/flags/KR.png", "PING": "30 ms", "PORT": 995, "UPTIME": "0 mins", "SESSIONS": 11, "LINE_QUALITY": "90.91 Mbps", "SCORE": 551787}, {"HOSTNAME": "vpn932879764.opengw.net", "LOCATION": "Korea Republic of", "FLAG": "https://raw.githubusercontent.com/FreeSSTP/server-list/main/flags/KR.png", "PING": "44 ms", "PORT": 1993, "UPTIME": "4 hours", "SESSIONS": 12, "LINE_QUALITY": "84.11 Mbps", "SCORE": 542305}, {"HOSTNAME": "vpn792608499.opengw.net", "LOCATION": "Korea Republic of", "FLAG": "https://raw.githubusercontent.com/FreeSSTP/server-list/main/flags/KR.png", "PING": "28 ms", "PORT": 995, "UPTIME": "0 mins", "SESSIONS": 0, "LINE_QUALITY": "70.06 Mbps", "SCORE": 541852}, {"HOSTNAME": "vpn222892714.opengw.net", "LOCATION": "Korea Republic of", "FLAG": "https://raw.githubusercontent.com/FreeSSTP/server-list/main/flags/KR.png", "PING": "28 ms", "PORT": 1689, "UPTIME": "0 mins", "SESSIONS": 1, "LINE_QUALITY": "352.00 Mbps", "SCORE": 536159}, {"HOSTNAME": "vpn538089916.opengw.net", "LOCATION": "European Union", "FLAG": "https://raw.githubusercontent.com/FreeSSTP/server-list/main/flags/EU.png", "PING": "67 ms", "PORT": 1339, "UPTIME": "8 hours", "SESSIONS": 6, "LINE_QUALITY": "48.85 Mbps", "SCORE": 517711}, {"HOSTNAME": "vpn672818639.opengw.net", "LOCATION": "Russian Federation", "FLAG": "https://raw.githubusercontent.com/FreeSSTP/server-list/main/flags/RU.png", "PING": "57 ms", "PORT": 1563, "UPTIME": "4 hours", "SESSIONS": 7, "LINE_QUALITY": "118.72 Mbps", "SCORE": 514754}, {"HOSTNAME": "vpn751433376.opengw.net", "LOCATION": "Russian Federation", "FLAG": "https://raw.githubusercontent.com/FreeSSTP/server-list/main/flags/RU.png", "PING": "36 ms", "PORT": 1693, "UPTIME": "13 hours", "SESSIONS": 4, "LINE_QUALITY": "23.24 Mbps", "SCORE": 513445}, {"HOSTNAME": "vpn255804131.opengw.net", "LOCATION": "United States", "FLAG": "https://raw.githubusercontent.com/FreeSSTP/server-list/main/flags/US.png", "PING": "17 ms", "PORT": 1768, "UPTIME": "0 mins", "SESSIONS": 24, "LINE_QUALITY": "201.60 Mbps", "SCORE": 500659}, {"HOSTNAME": "vpn926353783.opengw.net", "LOCATION": "United States", "FLAG": "https://raw.githubusercontent.com/FreeSSTP/server-list/main/flags/US.png", "PING": "20 ms", "PORT": 1810, "UPTIME": "2 days", "SESSIONS": 26, "LINE_QUALITY": "5.97 Mbps", "SCORE": 490461}, {"HOSTNAME": "vpn634947753.opengw.net", "LOCATION": "Thailand", "FLAG": "https://raw.githubusercontent.com/FreeSSTP/server-list/main/flags/TH.png", "PING": "36 ms", "PORT": 1615, "UPTIME": "4 hours", "SESSIONS": 7, "LINE_QUALITY": "26.87 Mbps", "SCORE": 486995}, {"HOSTNAME": "vpn977563878.opengw.net", "LOCATION": "Russian Federation", "FLAG": "https://raw.githubusercontent.com/FreeSSTP/server-list/main/flags/RU.png", "PING": "44 ms", "PORT": 1957, "UPTIME": "0 mins", "SESSIONS": 2, "LINE_QUALITY": "26.99 Mbps", "SCORE": 464448}, {"HOSTNAME": "vpn930356182.opengw.net", "LOCATION": "United States", "FLAG": "https://raw.githubusercontent.com/FreeSSTP/server-list/main/flags/US.png", "PING": "14 ms", "PORT": 1526, "UPTIME": "0 mins", "SESSIONS": 20, "LINE_QUALITY": "64.32 Mbps", "SCORE": 455517}, {"HOSTNAME": "vpn820995676.opengw.net", "LOCATION": "France", "FLAG": "https://raw.githubusercontent.com/FreeSSTP/server-list/main/flags/FR.png", "PING": "-", "PORT": 1515, "UPTIME": "0 mins", "SESSIONS": 0, "LINE_QUALITY": "164.84 Mbps", "SCORE": 421558}, {"HOSTNAME": "vpn346275605.opengw.net", "LOCATION": "Korea Republic of", "FLAG": "https://raw.githubusercontent.com/FreeSSTP/server-list/main/flags/KR.png", "PING": "-", "PORT": 1772, "UPTIME": "4 hours", "SESSIONS": 1, "LINE_QUALITY": "87.59 Mbps", "SCORE": 420595}, {"HOSTNAME": "vpn485966538.opengw.net", "LOCATION": "Korea Republic of", "FLAG": "https://raw.githubusercontent.com/FreeSSTP/server-list/main/flags/KR.png", "PING": "30 ms", "PORT": 1460, "UPTIME": "4 hours", "SESSIONS": 11, "LINE_QUALITY": "16.77 Mbps", "SCORE": 409603}, {"HOSTNAME": "vpn701547216.opengw.net", "LOCATION": "Japan", "FLAG": "https://raw.githubusercontent.com/FreeSSTP/server-list/main/flags/JP.png", "PING": "9 ms", "PORT": 1604, "UPTIME": "14 days", "SESSIONS": 15, "LINE_QUALITY": "95.08 Mbps", "SCORE": 386096}, {"HOSTNAME": "vpn912769876.opengw.net", "LOCATION": "Japan", "FLAG": "https://raw.githubusercontent.com/FreeSSTP/server-list/main/flags/JP.png", "PING": "18 ms", "PORT": 1247, "UPTIME": "13 days", "SESSIONS": 8, "LINE_QUALITY": "119.95 Mbps", "SCORE": 381275}]